materialsml/__init__.py
materialsml/main.py
materialsml/neuralnetwork/DGCNN.py
materialsml/neuralnetwork/__init__.py
materialsml/periph.py
materialsml-0.3.1.dist-info/METADATA
materialsml-0.3.1.dist-info/WHEEL
materialsml-0.3.1.dist-info/LICENSE
materialsml-0.3.1.dist-info/RECORD
