Metadata-Version: 2.1
Name: materialsml
Version: 0.3.1
Summary: A Machine Learning package for materials informatics
Author: andrewrgarcia
Author-email: garcia.gtr@gmail.com
Requires-Python: >=3.8,<3.9.0
Classifier: Programming Language :: Python :: 3
Classifier: Programming Language :: Python :: 3.8
Requires-Dist: boto3 (>=1.26.50,<2.0.0)
Requires-Dist: chardet (>=5.1.0,<6.0.0)
Requires-Dist: mp-api (>=0.30.5,<0.31.0)
Requires-Dist: mpcontribs-client (>=5.0.7,<6.0.0)
Requires-Dist: pytest (>=7.2.0,<8.0.0)
Requires-Dist: pyvista (>=0.37.0,<0.38.0)
Requires-Dist: stellargraph (==1.2.1)
